MANIFEST.in
README.rst
sass.cpp
sass.pyx
setup.py
libsass/.git
libsass/.gitignore
libsass/COPYING
libsass/INSTALL
libsass/LICENSE
libsass/Makefile
libsass/Makefile.am
libsass/Readme.md
libsass/ast.cpp
libsass/ast.hpp
libsass/ast_def_macros.hpp
libsass/ast_factory.hpp
libsass/ast_fwd_decl.hpp
libsass/backtrace.hpp
libsass/base64vlq.cpp
libsass/base64vlq.hpp
libsass/bind.cpp
libsass/bind.hpp
libsass/color_names.hpp
libsass/configure.ac
libsass/constants.cpp
libsass/constants.hpp
libsass/context.cpp
libsass/context.hpp
libsass/contextualize.cpp
libsass/contextualize.hpp
libsass/copy_c_str.cpp
libsass/copy_c_str.hpp
libsass/emscripten_wrapper.cpp
libsass/emscripten_wrapper.hpp
libsass/environment.hpp
libsass/error_handling.cpp
libsass/error_handling.hpp
libsass/eval.cpp
libsass/eval.hpp
libsass/expand.cpp
libsass/expand.hpp
libsass/extconf.rb
libsass/extend.cpp
libsass/extend.hpp
libsass/file.cpp
libsass/file.hpp
libsass/functions.cpp
libsass/functions.hpp
libsass/inspect.cpp
libsass/inspect.hpp
libsass/kwd_arg_macros.hpp
libsass/mapping.hpp
libsass/memory_manager.hpp
libsass/operation.hpp
libsass/output_compressed.cpp
libsass/output_compressed.hpp
libsass/output_nested.cpp
libsass/output_nested.hpp
libsass/parser.cpp
libsass/parser.hpp
libsass/paths.hpp
libsass/position.hpp
libsass/prelexer.cpp
libsass/prelexer.hpp
libsass/sass.cpp
libsass/sass.h
libsass/sass_interface.cpp
libsass/sass_interface.h
libsass/source_map.cpp
libsass/source_map.hpp
libsass/subset_map.hpp
libsass/to_c.cpp
libsass/to_c.hpp
libsass/to_string.cpp
libsass/to_string.hpp
libsass/token.hpp
libsass/trim.cpp
libsass/trim.hpp
libsass/units.cpp
libsass/units.hpp
libsass/utf8_string.cpp
libsass/utf8_string.hpp
libsass/util.cpp
libsass/util.hpp
libsass/sass2scss/sass2scss.cpp
libsass/sass2scss/sass2scss.h
libsass/sass2scss/tool/sass2scss.cpp
libsass/test/test_paths.cpp
libsass/test/test_selector_difference.cpp
libsass/test/test_specificity.cpp
libsass/test/test_subset_map.cpp
sass.egg-info/PKG-INFO
sass.egg-info/SOURCES.txt
sass.egg-info/dependency_links.txt
sass.egg-info/top_level.txt