Metadata-Version: 1.0
Name: sass
Version: 2.3
Summary: Python bindings for libsass
Home-page: https://github.com/pistolero/python-scss
Author: Sergey Kirilov
Author-email: sergey.kirillov@gmail.com
License: Apache License 2.0
Keywords: sass scss libsass
Platform: UNKNOWN
